asgi_redis/__init__.py
asgi_redis/core.py
asgi_redis/local.py
asgi_redis/sentinel.py
asgi_redis/twisted_utils.py
asgi_redis/tests/__init__.py
asgi_redis/tests/constants.py
asgi_redis/tests/test_core.py
asgi_redis/tests/test_local.py
asgi_redis/tests/test_sentinel.py
asgi_redis/tests/test_twisted.py
asgi_redis-1.4.2.dist-info/DESCRIPTION.rst
asgi_redis-1.4.2.dist-info/METADATA
asgi_redis-1.4.2.dist-info/RECORD
asgi_redis-1.4.2.dist-info/WHEEL
asgi_redis-1.4.2.dist-info/metadata.json
asgi_redis-1.4.2.dist-info/top_level.txt
