Metadata-Version: 1.0
Name: asgi-redis
Version: 1.4.2
Summary: Redis-backed ASGI channel layer implementation
Home-page: http://github.com/django/asgi_redis/
Author: Django Software Foundation
Author-email: foundation@djangoproject.com
License: BSD
Platform: UNKNOWN
